agilent34400multimeter/__init__.py
agilent34400multimeter/multimeter.py
agilent34400multimeter-0.1.4.dist-info/METADATA
agilent34400multimeter-0.1.4.dist-info/WHEEL
agilent34400multimeter-0.1.4.dist-info/top_level.txt
agilent34400multimeter-0.1.4.dist-info/RECORD
